README.rst
setup.py
qscollect/__init__.py
qscollect/__main__.py
qscollect/auth.py
qscollect/collector_base.py
qscollect/daemon.py
qscollect/db.py
qscollect.egg-info/PKG-INFO
qscollect.egg-info/SOURCES.txt
qscollect.egg-info/dependency_links.txt
qscollect.egg-info/entry_points.txt
qscollect.egg-info/namespace_packages.txt
qscollect.egg-info/top_level.txt
qscollect/collectors/__init__.py
qscollect/collectors/imap.py
qscollect/collectors/openpaths.py
qscollect/collectors/omnifocus/__init__.py
qscollect/collectors/omnifocus/_deltacalculator.py
qscollect/collectors/omnifocus/_omnidelta.py
qscollect/collectors/omnifocus/_omnientry.py
qscollect/collectors/omnifocus/_omnifocus.py
qscollect/collectors/omnifocus/collector.py
qscollect/collectors/omnifocus/helpers.py
qscollect/scripts/__init__.py
qscollect/scripts/config.py
qscollect/scripts/dump.py
tests/__init__.py
tests/collector_base_tests.py
tests/db_tests.py
tests/helpers.py
tests/imap_tests.py
tests/omnifocus_collector_tests.py
tests/omnifocus_data_tests.py