Metadata-Version: 1.0
Name: qscollect
Version: 1.1
Summary: A system for collecting Quantified Self data
Home-page: http://bitbucket.org/russellhay/qscollect
Author: Russell Hay
Author-email: me@russellhay.com
License: UNKNOWN
Platform: UNKNOWN
